kotcollections/__init__.py
kotcollections/__version__.py
kotcollections/kot_list.py
kotcollections/kot_map.py
kotcollections/kot_mutable_list.py
kotcollections/kot_mutable_map.py
kotcollections/kot_mutable_set.py
kotcollections/kot_set.py
kotcollections-0.1.4.dist-info/LICENSE
kotcollections-0.1.4.dist-info/METADATA
kotcollections-0.1.4.dist-info/WHEEL
kotcollections-0.1.4.dist-info/RECORD
