Metadata-Version: 2.3
Name: kotcollections
Version: 0.1.4
Summary: kotcollections is a Python library that fully reproduces Kotlin's Collections interfaces. It brings Kotlin's rich collection operations to Python developers with List, Set, and Map implementations.
License: MIT
Author: Vatis
Author-email: vatis@lalcs.com
Requires-Python: >=3.9
Classifier: License :: OSI Approved :: MIT License
Classifier: Programming Language :: Python :: 3
Classifier: Programming Language :: Python :: 3.9
Classifier: Programming Language :: Python :: 3.10
Classifier: Programming Language :: Python :: 3.11
Classifier: Programming Language :: Python :: 3.12
Classifier: Programming Language :: Python :: 3.13
Classifier: Development Status :: 4 - Beta
Classifier: Intended Audience :: Developers
Classifier: Topic :: Software Development :: Libraries :: Python Modules
Classifier: Typing :: Typed
Project-URL: Bug Tracker, https://github.com/Lalcs/kotcollections/issues
Project-URL: Homepage, https://github.com/Lalcs/kotcollections
Project-URL: Repository, https://github.com/Lalcs/kotcollections
